data_prep/__init__.py
data_prep/dataprep.py
tydataprep/__init__.py
tydataprep/tydataprep.py
tydataprep-0.3.dist-info/LICENSE
tydataprep-0.3.dist-info/METADATA
tydataprep-0.3.dist-info/WHEEL
tydataprep-0.3.dist-info/top_level.txt
tydataprep-0.3.dist-info/RECORD
